cdk_project_constructs/__init__.py
cdk_project_constructs/ddbt.py
cdk_project_constructs/kms.py
cdk_project_constructs/lmb.py
cdk_project_constructs/s3.py
cdk_project_constructs/sns.py
cdk_project_constructs/sqs.py
cdk_project_constructs/schemas/__init__.py
cdk_project_constructs/schemas/configuration_vars.py
cdk_project_constructs/stacks/__init__.py
cdk_project_constructs/stacks/code_quality_stack.py
cdk_project_constructs/stacks/governance_stack.py
cdk_project_constructs/stacks/infrastructure_tests_stack.py
cdk_project_constructs/stacks/integration_tests_stack.py
cdk_project_constructs/stacks/notifications_stack.py
cdk_project_constructs/stacks/pipeline_plugins_stack.py
cdk_project_constructs/stacks/pipeline_trigger_stack.py
cdk_project_constructs/stages/__init__.py
cdk_project_constructs/stages/code_quality_stage.py
cdk_project_constructs/stages/infrastructure_tests_stage.py
cdk_project_constructs/stages/integration_tests_stage.py
cdk_project_constructs/stages/notifications_stage.py
cdk_project_constructs/stages/plugins_stage.py
cdk_project_constructs/stages/shared_resources_stage.py
cdk_project_constructs/utils/__init__.py
cdk_project_constructs-1.0.10.dist-info/licenses/LICENSE
cdk_project_constructs-1.0.10.dist-info/METADATA
cdk_project_constructs-1.0.10.dist-info/WHEEL
cdk_project_constructs-1.0.10.dist-info/top_level.txt
cdk_project_constructs-1.0.10.dist-info/RECORD
