Metadata-Version: 2.4
Name: cdk-project-constructs
Version: 1.0.10
Summary: AWS CDK resources to be used in infra projects.
Author: Madrag
License: MIT
Requires-Python: >=3.13
License-File: LICENSE
Requires-Dist: aws-cdk-lib>=2.159.0
Requires-Dist: constructs<11.0.0,>=10.0.0
Requires-Dist: cdk-monitoring-constructs>=8.3.0
Requires-Dist: pyyaml>=6.0.2
Requires-Dist: pydantic>=2.9.2
Requires-Dist: pydantic-core>=2.23.4
Requires-Dist: build>=1.2.2
Dynamic: author
Dynamic: description
Dynamic: description-content-type
Dynamic: license
Dynamic: license-file
Dynamic: requires-dist
Dynamic: requires-python
Dynamic: summary
